markovchatter.py
markovchatter-1.1.dist-info/LICENSE
markovchatter-1.1.dist-info/METADATA
markovchatter-1.1.dist-info/WHEEL
markovchatter-1.1.dist-info/entry_points.txt
markovchatter-1.1.dist-info/top_level.txt
markovchatter-1.1.dist-info/RECORD
