Metadata-Version: 2.1
Name: markovchatter
Version: 1.1
Summary: Easy Markov chain text generator.
Home-page: https://bitbucket.org/emptypage/markovchatter/
Author: Masaaki Shibata
Author-email: mshibata@emptypage.jp
License: MIT
Keywords: markov,chain,text
Classifier: Programming Language :: Python :: 3.10
Classifier: License :: OSI Approved :: MIT License
Classifier: Operating System :: OS Independent
License-File: LICENSE
Requires-Dist: flask
Requires-Dist: markovify
